kiam_astro/FKIAMToolbox.cpython-312-x86_64-linux-gnu.so
kiam_astro/JPLEPH
kiam_astro/__init__.py
kiam_astro/dace.py
kiam_astro/kiam.py
kiam_astro/optimal.py
kiam_astro/trajectory.py
kiam_astro/images/Earth.jpg
kiam_astro/images/Earth2.jpg
kiam_astro/images/Moon - Plate Caree Projection.jpg
kiam_astro/images/Moon1.jpg
kiam_astro/images/Moon2.jpg
kiam_astro.libs/libgfortran-5b574c8a.so.5.0.0
tests/__init__.py
tests/test_kiam_basic.py
kiam_astro-6.0.2.dist-info/METADATA
kiam_astro-6.0.2.dist-info/WHEEL
kiam_astro-6.0.2.dist-info/top_level.txt
kiam_astro-6.0.2.dist-info/RECORD
kiam_astro-6.0.2.dist-info/sboms/auditwheel.cdx.json
